[
    {"displayName": "Test JSON Quest",
     "description": "A test quest for loading from JSON",
     "maxTimeTaken": 10,
     "requirements": [],
     "onComplete": [{"type": "setVisibleOverride", "target": 2}]
     },
     {"displayName": "Test JSON Quest 2",
      "description": "The second quest for loading from JSON",
      "maxTimeTaken": 100,
      "requirements": []},
     {"displayName": "Test JSON Quest 3",
      "description": "The third quest for loading from JSON",
      "maxTimeTaken": 200,
      "requirements": [1],
      "visible": false},
     {"displayName": "Test JSON Quest 4",
      "description": "The second quest for loading from JSON",
      "maxTimeTaken": 50,
      "requirements": []},
     {"displayName": "Test Website Quest 2",
      "description": "The second website test quest.",
      "maxTimeTaken": 1000000000000,
      "requirements": [0,1,2,3],
      "visibleOverride": true}
]
